peakrdl_beam/__about__.py
peakrdl_beam/__init__.py
peakrdl_beam/__peakrdl__.py
peakrdl_beam/beam_languages.py
peakrdl_beam/erlang_header.py
peakrdl_beam/erlang_module.py
peakrdl_beam/exporter.py
peakrdl_beam/identifier_filter.py
peakrdl_beam/scanner.py
peakrdl_beam/state.py
peakrdl_beam/utils.py
peakrdl_beam/templates/header.hrl
peakrdl_beam/templates/module.erl
peakrdl_beam-0.1.1.dist-info/LICENSE
peakrdl_beam-0.1.1.dist-info/METADATA
peakrdl_beam-0.1.1.dist-info/WHEEL
peakrdl_beam-0.1.1.dist-info/entry_points.txt
peakrdl_beam-0.1.1.dist-info/top_level.txt
peakrdl_beam-0.1.1.dist-info/RECORD
