Metadata-Version: 2.1
Name: peakrdl-beam
Version: 0.1.1
Summary: Generate Erlang or Elixir modules from a SystemRDL register model
Author: João Henrique Ferreira de Freitas
License: GNU GENERAL PUBLIC LICENSE
Project-URL: Source, https://github.com/joaohf/PeakRDL-beam
Project-URL: Tracker, https://github.com/joaohf/PeakRDL-beam/issues
Project-URL: Changelog, https://github.com/joaohf/PeakRDL-beam/releases
Project-URL: Documentation, https://peakrdl-beam.readthedocs.io/
Keywords: SystemRDL,PeakRDL,CSR,compiler,tool,registers,generator,Erlang,Elixir,BEAM,software
Classifier: Development Status :: 2 - Pre-Alpha
Classifier: Programming Language :: Python
Classifier: Programming Language :: Python :: 3
Classifier: Programming Language :: Python :: 3.6
Classifier: Programming Language :: Python :: 3.7
Classifier: Programming Language :: Python :: 3.8
Classifier: Programming Language :: Python :: 3.9
Classifier: Programming Language :: Python :: 3.10
Classifier: Programming Language :: Python :: 3.11
Classifier: Programming Language :: Python :: 3.12
Classifier: Programming Language :: Python :: 3 :: Only
Classifier: Intended Audience :: Developers
Classifier: License :: OSI Approved :: GNU General Public License v3 (GPLv3)
Classifier: Operating System :: OS Independent
Classifier: Topic :: Scientific/Engineering :: Electronic Design Automation (EDA)
Requires-Python: >=3.6
License-File: LICENSE
Requires-Dist: systemrdl-compiler <2,>=1.21.0
Requires-Dist: jinja2
